dddjango/__init__.py
dddjango-0.0.1.dist-info/LICENSE
dddjango-0.0.1.dist-info/METADATA
dddjango-0.0.1.dist-info/WHEEL
dddjango-0.0.1.dist-info/RECORD
